pfun_path_helper/__init__.py
pfun_path_helper-0.1.4.dist-info/METADATA
pfun_path_helper-0.1.4.dist-info/WHEEL
pfun_path_helper-0.1.4.dist-info/top_level.txt
pfun_path_helper-0.1.4.dist-info/RECORD
