Metadata-Version: 2.4
Name: pfun-path-helper
Version: 0.1.4
Summary: Path helper-- eases local package development; appends package-relevant paths to 'sys.path'.
Author-email: Robbie Capps <rocapp@gmail.com>
Requires-Python: <3.13,>3.11
Requires-Dist: build>=1.0.3
Requires-Dist: setuptools>=68.2.2
Requires-Dist: uv>=0.7.13
Provides-Extra: dev
Requires-Dist: pytest>=7.4.2; extra == "dev"
Requires-Dist: ipython>=8.16.1; extra == "dev"
Requires-Dist: tox>=3.23.0; extra == "dev"
